{
  "id": "W4313595551",
  "metadata": {
    "title": "A Systematic Review on the Metaverse-Based Blended English Learning",
    "n_sections": 11,
    "n_subsections": 19,
    "n_subsubsections": 4,
    "n_tables": 0
  },
  "sections": [
    {
      "section_id": "s_1",
      "section_index": 1,
      "section_label": "Keywords",
      "subsections": [],
      "subsubsections": [],
      "text": "metaverse, blended English learning, learner engagement, learning outcome, digital literacy, challenges",
      "citations": [],
      "tables_in_text": []
    },
    {
      "section_id": "s_2",
      "section_index": 2,
      "section_label": "1. Introduction",
      "subsections": [],
      "subsubsections": [],
      "text": "Over the past two decades, various digital technologies have been applied to sustain higher education [W4200069166]. The significance of technological advancements has been highlighted to support digital learning during the post-pandemic era [UNMAPPED:2]. Recently, the metaverse has been a recurring theme to be considered a new direction to promote education [W4206538191]. The metaverse as a three-dimensional-based (3D) virtual reality has been considered to adapt to education, especially blended learning, although the metaverse is not a new concept [W4226350846]. Researchers and educators have discussed the implication of the metaverse for blended learning [W4200069166]. The COVID-19 pandemic accelerated the acceptance of the metaverse technology in some leading universities in China and worldwide [W2136300094, W2308389019, W2311780104, W2588446734, W2997767409, W2967947007, W4293084330]. It is necessary to investigate the effects of the metaverse on blended learning.\n\nMoreover, metaverse-based technology plays a significant role in blended learning in higher education contexts [W3109876850]. It allows learners to interact with each other socially [UNMAPPED:13]. The metaverse-based technology facilitates learning regardless of learners' location, tacitly promoting learners' academic performance, coupled with leisure and education [W4206283216]. A different aspect of the metaverse compared to traditional information and communication technology is that it creates a virtual world outside the traditional classroom [UNMAPPED:13]. The immersive virtual world can potentially improve active and creative learning, as learners have been no strangers to the virtual environment since the beginning of 2020 [UNMAPPED:13]. The visual aspect of the metaverse and the possibility of real-time change benefit learning by amplifying learner imagination and intelligence [W4295788720]. Therefore, there is a need to explore integrating metaverse-based technology into learning.\n\nHowever, the metaverse has not been fully explored [W1583636700]. The metaverse is still in its infancies [W2588446734]. A lack of literature summarized the findings of immersing the metaverse with blended English learning and even less provided essential insights into current and future English instructional guidance [W4206460460, W4320070415]. Hence, several questions have not been answered, such as what assessing factors are used in the metaverse; or what challenges are in adopting the metaverse to blended English learning. Consequently, this study aims to conduct a systematic review of the metaverse applied to blended English learning to fill the research gap. This study conducts bibliometric and content analysis to investigate metaverse-based blended English learning.\n\nThis study aims to investigate metaverse-based blended English learning and provide guidance for current English education in higher education. As blended English learning cannot be explained without technologies [W2257545119], this study selects several possible factors to understand what learners' learning performance is in metaverse-based blended English learning, what degree of learners' engagement in the virtual environments, what about the digital literacy of instructors and learner, and what the urgent issues are in the metaverse technologies. The contribution of this study is to know learners' benefits or any discomforts in metaverse-based blended English learning. Thus, this study might provide beneficial tips for researchers and educators to further study metaverse-based education.",
      "citations": [
        "W4200069166",
        "W4206538191",
        "W4226350846",
        "W3109876850",
        "W4206283216",
        "W4295788720",
        "W1583636700",
        "W2588446734",
        "W4206460460",
        "W4320070415",
        "W2257545119"
      ],
      "tables_in_text": [],
      "citations_unmapped": [
        "2",
        "13"
      ]
    },
    {
      "section_id": "s_3",
      "section_index": 3,
      "section_label": "2. The Need for the Study",
      "subsections": [
        {
          "subsection_id": "s_3_1",
          "subsection_index": 1,
          "subsection_label": "2.1. Metaverse",
          "subsubsections": [],
          "text": "Metaverse is an immersive three-dimensional (3D) virtual reality where multi-user as avatars interact and tend to create artificial societies in an online environment [W1583636700, W3109876850, W4200069166]. Avatars, software agents, are our alter egos [W4200069166]. Virtual reality is a metaphor for the real world in which people engage daily activities and economic life through avatars [W4200069166]. The metaverse denotes a world where social, economic, and cultural activities are conducted without barriers to collaboration [W4206538191]. It is different from the physical world. There is no agreed-upon definition of metaverses [W1583636700]. Extensive studies have provided substantial evidence about the potential contribution to knowledge in several areas, such as unique technology capabilities and a deeper understanding of virtual collaboration.",
          "citations": [
            "W1583636700",
            "W3109876850",
            "W4200069166",
            "W4206538191"
          ],
          "tables_in_text": []
        },
        {
          "subsection_id": "s_3_2",
          "subsection_index": 2,
          "subsection_label": "2.2. Characteristics",
          "subsubsections": [],
          "text": "The virtual reality metaverses have mainly three essential characteristics: interactivity, embodiment, and persistence [W2101431782, W3109876850, W4200069166, W4225434615, W4224253557]. First, interactivity makes users interact and communicate with others in the metaverse through their avatars [W2087271322]. Users impact the unrealistic objects and exert an influence on the opinions and behaviors of others; the appearance of avatars can reflect users' sense of presence and outcomes in virtual teams, which is reciprocal [W2132619666, W2106968553, W3109876850]. Interactivity is the extent to which users can involve; it expands the possibility of individual or worldwide interaction [W3109876850]. Second, embodiment implies that avatars represent users in the metaverse [W2132619666]. It symbolizes the participants' presence, including their suppositional environment and how avatars and the environment interact. The more realistic representation, the stronger the sense of presence and immersion, and the greater the users' engagement in the metaverse in contrast with face-to-face interactions [W2132619666]. Third, persistence ensures the continuity of data (e.g., the position, conversations, property objects) to be saved. Moreover, data can be retrieved easily once the participants are reconnected or not connected to the virtual world [W4296112744]. The metaverse platform continues to function and develop even after the users have departed from the virtual world [W4225434615].",
          "citations": [
            "W2101431782",
            "W3109876850",
            "W4200069166",
            "W4225434615",
            "W4224253557",
            "W2087271322",
            "W2132619666",
            "W2106968553",
            "W4296112744"
          ],
          "tables_in_text": []
        },
        {
          "subsection_id": "s_3_3",
          "subsection_index": 3,
          "subsection_label": "2.3. Education-Based Metaverse for the Blended English Learning",
          "subsubsections": [],
          "text": "The immersive technology of the metaverse brings about the new possibility of blended learning [W2758953075, W4200069166]. The infinite potential metaverse for educational applications may be an ideal replenishment for blended English learning [W2150584409]. The metaverse further breaks the limitations of online learning in access to knowledge [W2759268923]. The application of the education-based metaverse as the virtual classroom can be incorporated with face-to-face learning. A blended learning approach uses online learning facilitated the metaverse-based applications in a real classroom, creating an authentic English learning environment for learners [W2759268923]. An added value of using the metaverse in a blended learning environment is that it can develop learners' critical thinking and problem-solving, consistent with learning values and higher education teaching [W2114003275].\n\nEducation-based metaverse refers to using metaverse-based platforms to improve learning activities [W2757450262]. The education-based metaverse creates an immersive environment that engages English learners in an authentic learning atmosphere [W2588446734]. In addition, the potential of the education-based metaverse can foster the development of skills needed by English learners [W2273638022, W2757450262]. Such skills are the ability to collaborate with others, effective communication, and creative problem-solving [W2114058809, W2131552753]. There are mainly five primary affordances of the education-based metaverse in English learning and teaching: the acquirement of English knowledge, the promotion of deep English learning activities, the enhancement of intrinsic motivation, sufficient provision of English learning opportunities, the improvement of self-efficacies, and the boost of rich and compelling collaborative English learning tasks from the virtual world [W2114058809, W2588446734].",
          "citations": [
            "W2758953075",
            "W4200069166",
            "W2150584409",
            "W2759268923",
            "W2114003275",
            "W2757450262",
            "W2588446734",
            "W2273638022",
            "W2114058809",
            "W2131552753"
          ],
          "tables_in_text": []
        },
        {
          "subsection_id": "s_3_4",
          "subsection_index": 4,
          "subsection_label": "2.4. Learner Engagement in the Education-Based Metaverse",
          "subsubsections": [],
          "text": "The term engagement in the context of education-based metaverse means user engagement or learner engagement [W4246277771, W2005190935]. At the same time, the terms (student engagement, school engagement, or learner engagement) are utilized in teaching and learning [W2018176383, W2502573359, W2286110194]. User engagement has become a significant factor in effective predict learner responses to a given learning task in the behavioral, emotional, and cognitive aspects [W2018176383]. The education-based metaverse is considered a means to enhance user engagement for English learners at university [W2758126666]. In addition, the education-based metaverse offers a perfect, engaging visual environment, especially for young English learners [W2758126666].\n\nBased on the education-based metaverse, English users' engagement can be improved as they are offered immersive and interactive experiences through a virtual environment [W4206460460, W4320070415]. English users can flexibly and study relatively quickly due to no physical restriction in the real world, which tend to elevate the engagement level of English learners [W2758126666]. All English learners are independent and can actively conduct action plans [W4293168945]; thus, they are more engaged in achieving learning goals in education-based metaverse environments [W4206460460, W4320070415]. The metaverse can provide technical support and autonomous tutoring systems, which help learners to establish correlations between virtual objects and experiments for English courses. So it provides new possibilities for engagement in learning the English language [W3155331735, W4206460460, W4320070415].\n\nHowever, some literature put forth no direct relationship between the perception of engagement of English users and virtual worlds based on the new education-based metaverse [W2121475339, W2758126666]. Such engagement does not necessarily indicate language learning. There is also a concern that user engagement perhaps translates to off-task thoughts rather than English learning [W2502573359]. Furthermore, time on distracting entertainment in game-based environments is wrongly reputed to be engagement but not English learning [W2127199677]. Therefore, there is a clear need for further demonstration in blended English learning.",
          "citations": [
            "W4246277771",
            "W2005190935",
            "W2018176383",
            "W2502573359",
            "W2286110194",
            "W2758126666",
            "W4206460460",
            "W4320070415",
            "W4293168945",
            "W3155331735",
            "W2121475339",
            "W2127199677"
          ],
          "tables_in_text": []
        },
        {
          "subsection_id": "s_3_5",
          "subsection_index": 5,
          "subsection_label": "2.5. Learning Outcomes in the Immersive Virtual Worlds of the Education-Based Metaverse",
          "subsubsections": [],
          "text": "Immersion can be regarded as the subjective impression that a user submerses into a virtual environment, which is a loose psychological concept or an experience [W2096438128, W1970332800, W2273638022]. In the education-based metaverse, successful temporal immersion in virtual teams is usually connected with higher performance [W1583636700, W2759268923]. The metaverse-based platforms support English learners with an overall immersive virtual learning environment which can be considered an educational simulation [W1970332800, W2030722826]. English learners can \"meet\" real people on the metaverse and communicate with them in their target language. In addition, Avatar representation can enhance English communication skills, whilst virtual worlds afford navigational and socialization tools which improve user presence [W2139782915]. Immersion experience in 3D virtual worlds can support complex thinking, facilitate learning a second language, and positively influence better English learning outcomes [W2257545119].\n\nExtensive descriptive research focused on English learning outcomes on the education-based metaverse [W2283313983, W2257545119]. However, there is a lack of sufficient experimental research that may provide detailed data on ways the education-based metaverse could be utilized in English education. Furthermore, compared to limitations and inefficiencies in 2D learning environments, it is necessary to explore whether an immersive learning experience in the metaverse is advantageous in online learning [W3206147266]. Therefore, this research attempts to discover immersive atmospheres in 3D virtual worlds, which significantly aid English learning outcomes.",
          "citations": [
            "W2096438128",
            "W1970332800",
            "W2273638022",
            "W1583636700",
            "W2759268923",
            "W2030722826",
            "W2139782915",
            "W2257545119",
            "W2283313983",
            "W3206147266"
          ],
          "tables_in_text": []
        },
        {
          "subsection_id": "s_3_6",
          "subsection_index": 6,
          "subsection_label": "2.6. Digital Literacy",
          "subsubsections": [
            {
              "subsubsection_id": "s_3_6_1",
              "subsubsection_index": 1,
              "subsubsection_label": "2.6.1. The Aim of the Study",
              "parent_subsection_id": "s_3_6",
              "text": "Considering the metaverse as the new resource for the blended English learning, we propose the following research questions:\n\nRQ1: Can the education-based metaverse promote English user engagement?\n\nRQ2: Can the immersive virtual worlds of the education-based metaverse promote English learning outcomes?\n\nRQ3: Is digital literacy an essential construct in metaverse-based blended English learning?\n\nRQ4: What are the challenges on metaverse-based platforms?",
              "citations": [],
              "tables_in_text": []
            }
          ],
          "text": "Digital literacy is an important factor that may determine whether metaverse-based applications can be used to sustain education, which is related to the capabilities of learners in using the metaverses [W1583636700, W4221094847]. To a certain degree, digital literacy influences instructors' and learners' intentions to participate in metaverse-based applications [W3216203764]. Digital literacy plays a vital role in Metaverse experience environments. Familiarity with metaverse-based applications leads to excitement and readiness for the sustainability of language learning. So instructors and learners need to increase their degree of digital literacy to use education-based metaverse flexibility [W4296112744].\n\nDigital literacy on metaverse-based platforms can be considered a requirement for instructors and learners to skillfully use interaction techniques and acquire knowledge in virtual and physical environments [W3041286989]. Digital literacy determines whether instructors and learners can access immersive learning environments and efficiently focus on English learning tasks in metaverse-based applications [W2064369906]. Consequently, digital literacy exerts an important impact on learners' ability to carry out their daily adoption of metaverse technologies in a successful way [W2621810281]. Digital literacy can be improved by school training instructors and learners [W4291466020]. In addition, an external effect such as institutional support ensures that instructors' and learners' digital literacy can be enhanced smoothly [W2287583712, W2905188234]. Moreover, previous studies reveal that instructors and learners should be a good grip on the entire scheme of information handling and audiovisual equipment [W2906697699]. In particular, English instructors and learners should be familiar with digital pedagogical tools to meet the needs of English courses in terms of digital literacy [W4295873136]. For English instructors and learners, it is an important ability to acquire knowledge and language skills in metaverse-based blended learning.\n\nBased on related work, the metaverse-based technology has opened new possibilities for innovation in blended English learning [W3109876850]. In this sense, this study seeks to reproduce participation from the engagement perspective in an immersive virtual metaphor environment. In addition, engagement activities can be used to predict learners' learning outcomes. As learners become more engaged with technology-based learning and learning materials, their learning will increase [W2108617939]. This study suggests the potential of the metaverse as digital skills that support possible knowledge increase. However, the metaverse may raise daunting challenges on learners' and instructors' digital competence [W4206283216]. It is necessary to demonstrate a digital literacy level that motivates learners and instructors in their training. Meanwhile, digital literacy has become a significant driver in the choice of academic resources in blended language learning [W3109876850]. A learner may be pushed away due to the challenges during metaverse-based learning [W4311106110]. With this in mind, we proposed alternative research questions.",
          "citations": [
            "W1583636700",
            "W4221094847",
            "W3216203764",
            "W4296112744",
            "W3041286989",
            "W2064369906",
            "W2621810281",
            "W4291466020",
            "W2287583712",
            "W2905188234",
            "W2906697699",
            "W4295873136",
            "W3109876850",
            "W2108617939",
            "W4206283216",
            "W4311106110"
          ],
          "tables_in_text": []
        }
      ],
      "subsubsections": [],
      "text": "",
      "citations": [],
      "tables_in_text": []
    },
    {
      "section_id": "s_4",
      "section_index": 4,
      "section_label": "3. Methods",
      "subsections": [],
      "subsubsections": [],
      "text": "This study adopted a systematic literature review on the current studies on the metaverse in English education. By a rapid evidence assessment, a four-step method was conducted to ensure that outcome reporting bias may be avoided because the interpretation of results tended to be subjective in manual censorship [W2515112257]. So the study took a traditional bibliometric combined with a mixed-method systematic review and content analysis to identify the articles [W4206460460, W4320070415]. The four steps were as follows:\n\n* We planned the research themes and designed the research questions. The study got access to literature through widely searching for online databases. We obtained related literature through an extensive search for online databases. The search strings used in both Web of Science and Scopus databases were: metaverse (Topic) OR metaverse and education (Topic) OR metaverse and learn*(Topic) OR metaverse and English learn*(Topic) OR metaverse and English teach*(Topic). The data included academic articles published until October 2022.\n\nThe study used clustering and mapping techniques in VOSviewer to verify research questions [UNMAPPED:64]. VOSviewer is a software tool for constructing networks of scientific journals, keywords, or terms, which is mainly used for analyzing bibliometric networks through bibliographic coupling, co-authorship, co-occurrence, citation, or co-citation link [UNMAPPED:64]. VOSviewer can primarily create visualized maps based on network data, which reflects research trends and hotspots among network and bibliographic database files [UNMAPPED:64]. In this case, we selected the proposed research questions based on the scientific analysis of the full detailed output from VOSviewer. The study outputs the results (N = 262) in plain text and analyzes them via VOSviewer. Co-occurrence was selected as the analysis type; all keywords were chosen as the analysis unit. Full counting was used as the counting method. The minimum number of occurrences of a keyword was set at three. Of the 1,202 keywords, 84 met the threshold and were classified into six clusters (Figure 1). Cluster 1 included 17 items, e.g., benefits, bitcoin, blockchain, COVID-19, creation, cryptocurrency, customer experience, framework, governance, mental health, metaverse, privacy, systems, technology, trust, utopia. Cluster 2 included 13 items, e.g., artificial intelligence, avatar, avatars, big data, blockchains, deep learning, digital twin, games, information, machine learning, simulation, solid modeling, and virtual world. Cluster 3 included 12 items, e.g., acceptance, communication, emotions, environments, experience, immersion, impact, intention, model, reality, self, and telepresence. Cluster 4 included 12 items, e.g., augmented reality, definition, digital twins, e-commerce, extended reality, learning, mixed reality, science, support, technologies, virtual reality, and VR. Cluster 5 included 8 items, e.g., bibliometric, design, industry, internet, management, skin, and visualization. Cluster 6 included 8 items, e.g., behavior, collaboration, environment, metaverses, performance, second life, social presence, and virtual worlds. Cluster 7 included 8 items, e.g., education, gamification, mathematical models, online, satisfaction, students, technology acceptance, and virtual environments. Cluster 8 included 6 items, e.g., Facebook, meta, sensors, social media, system, and virtual reality.\n\nWe calculated the total strength of the co-occurrence links with other key-words, and obtained a list of keywords with the top number of co-occurrence and link strength, among which the researchers found closely related keywords: metaverse (N = 126, link strength = 371), virtual reality (N = 47, link strength = 192), immersion (N = 5, link strength = 31), students (N = 5, link strength = 42), education (N = 7, link strength = 30), performance (N = 5, link strength = 28), learning (N = 3, link strength = 15). The study will evolve the topic based on these keywords and metaverse-based applications' challenges.\n\nTo deal with this complex topic, we included and excluded the obtained results based on the Preferred Reporting Items for Systematic Review (PRISMA) [W2005501262] (Figure 2). PRISMA is adopted to allow researchers to estimate the applicability and credibility of the review findings [W3123893780]. It is designed for strictly evaluating and systematically reviewing research findings. The checklist items of PRISMA help facilitate and complete reporting of systematic reviews. In addition, the researchers used a critical appraisal tool (STARLITE) to score each selected article [W3097237491]. STARLITE is already widely acknowledged as important in recording literature searches [W1562929073]. Thus, reports of systematic reviews could be trustworthy. Complete literature should include a title, abstract, introduction, literature review, methods, results, discussion, and conclusion. The researchers worked out guidelines for systematic reviews. Two researchers collaborated to review the literature with high inter-rater reliability (k = 0.91). If they cannot agree on any decision, a third international researcher will be invited to determine the selection. A study was included if it (1) focused on metaverse-based education; (2) provided enough information for the study, or (3) arrived at clear conclusions. A study was excluded if it: (1) discussed metaverse in general and not in education; (2) was not in English; and (3) was not accessible online. As a result, 262 studies in the Web of Science database and 15 in the Scopus database were identified.",
      "citations": [
        "W2515112257",
        "W4206460460",
        "W4320070415",
        "W2005501262",
        "W3123893780",
        "W3097237491",
        "W1562929073",
        "W4200069166",
        "W4206538191"
      ],
      "tables_in_text": [],
      "citations_unmapped": [
        "64",
        "2"
      ]
    },
    {
      "section_id": "s_5",
      "section_index": 5,
      "section_label": "4. Results",
      "subsections": [
        {
          "subsection_id": "s_5_1",
          "subsection_index": 1,
          "subsection_label": "4.1. The Metaverse-Based Blended English Learning",
          "subsubsections": [],
          "text": "The metaverse-based blended English learning will improve the depth and breadth of English learning activities and speed the development of teaching-learning relationships [W4224253557]. It is likely to fundamental reshape English education [UNMAPPED:2]. The issue of how to innovate blended learning has appeared significant during the post-pandemic era [W4244811727, W4221094847]. At the same time, the education-based metaverse develops and fulfills all educators' imaginations [W2588446734]. Learners can communicate via avatars by applying audio- or text-based tools. Immersive 3D language learning environments enhance learners' engagement and better learning performance [W4295788720]. Virtual interaction with the content they favor stimulates learners' intuition and willingness. Learners can share information and receive multifaceted feedback. Learners can improve their intercultural communication level and problem-solved skills through avatars, which can bring learners satisfaction improvement and English academic success [W4200069166]. Moreover, instructors can offer learners high-quality education, and learners' needs can be fully fulfilled in virtual classroom environments [W3109876850]. Thus, the traditional teaching-learning relationships can be significantly improved.\n\nHowever, researchers have concerns that the mixture of the metaverse in education is a hoax. Because today's technology lacks trust and knowledge, the metaverse should not be applied to education on a large scale [W4294865070, W4224216565, UNMAPPED:2]. Moreover, the value of the education-based metaverse lacks sufficient confirmation, affecting its application to education [W4224253557]. Still, there is a lack of systematic review on the educational value of using the metaverse [W4224253557].\n\n**FIGURE 1** Clustering keywords related to the metaverse-based applications.",
          "citations": [
            "W4224253557",
            "W4244811727",
            "W4221094847",
            "W2588446734",
            "W4295788720",
            "W4200069166",
            "W3109876850",
            "W4294865070",
            "W4224216565"
          ],
          "tables_in_text": [],
          "citations_unmapped": [
            "2"
          ]
        },
        {
          "subsection_id": "s_5_2",
          "subsection_index": 2,
          "subsection_label": "4.2. RQ1: Can the Education-Based Metaverse Promote English User Engagement?",
          "subsubsections": [],
          "text": "The online 3-D virtual metaverse can affect learners' levels of engagement [W2758126666]. It has been proven through several studies that the metaverse provides users engaging in myriad learning activities, such as language classes (see, e.g., [W1999256366, W2759268923, W4226474524]). Multiple modes of interaction in physical and virtual worlds make the metaverse an ideal tool for examining user engagement [W1999256366]. Even though some learners may feel physical isolation, they can actively create avatars and participate in social or educational activities with other avatars [W4226474524]. Although literature concerns that English learner engagement may be related to game-based environments in the metaverse rather than deep learning, some empirical studies have proved that a user learning environment with the gameplay design is critical to ensure engagement that leads to language learning and academic achievements [W2758126666]. In the context of English education in China, user engagement in learning English as a foreign language can improve via 3D avatar interactions in virtual space [W2150584409].\n\nThe metaverse as an intercultural 3D online environment affords English learners to engage in purposeful virtual online activities through avatar-based perceptual learning [W1993410685]. Furthermore, high levels of user engagement usually mean more freedom and effective manipulation in virtual environments [W2139782915]. English learners can study performance, tourism, and exhibitions in virtual English spaces based on a high degree of self-engagement, which can directly influence or indirectly affect learning outcomes [W4200069166]. Interestingly, the learner engagement degree may lower at the beginning period of utilizing the metaverse technology. Some learners feel thwarted about English learning in an immersive virtual environment, but they can adapt to an appealing, inclusive online platform [W2759268923].\n\n**FIGURE 2** A flowchart of the literature inclusion and exclusion based on the PRISMA protocol.",
          "citations": [
            "W2758126666",
            "W1999256366",
            "W2759268923",
            "W4226474524",
            "W2150584409",
            "W1993410685",
            "W2139782915",
            "W4200069166"
          ],
          "tables_in_text": []
        },
        {
          "subsection_id": "s_5_3",
          "subsection_index": 3,
          "subsection_label": "4.3. RQ2: Can the Immersive Virtual Worlds in the Education-Based Metaverse Promote English Learning Outcomes?",
          "subsubsections": [],
          "text": "Virtual worlds in the metaverse empower learners' learning outcomes and increase the overall personal learning experience [W4291109444, UNMAPPED:2]. In the context of English education, the metaverse enables learners to construct English knowledge and discourses with peers in virtual worlds, which makes it easy for learners to produce English academic achievement [W2758953075]. In addition, with virtual reality, \"real world\" online chatting, learners gain a powerful channel to learn English [W4225434615]. Thus, metaverse-based blended English learning can be an appropriate way to accomplish English learning tasks [W2757450262]. In particular, the education-based metaverse creates an immersive learning environment similar to a real classroom [W2204765864]. English learners can apply their knowledge to solving complicated problems that are the same as those in a physical learning environment [W2257545119]. Especially in English vocabulary and grammar learning, virtual environments can provide learners with synchronous interaction and competency-based training, which is quite different from other online language learning tools [W2588446734].\n\nThe metaverse technologies make English education more attractive because they support immersive learning [W2500783958]. The current metaverse has shown unique advantages in promising results of English learning achieved by learners' immersive learning and their avatars (virtual persons). It has to be interestingly mentioned that immersion in metaverse-based technologies involves objective features of superb instructional styles that can bring learners an amazing, immersive experience [W2036383665]. Immersion is not a psychological sense of being there, but it can objectively assess the degree of a system's virtual environment [W4224253557]. Immersive virtual environments in the metaverse are projected to boost learners' learning to be more engaging and lifelike in unfamiliar circumstances [W4280521113, UNMAPPED:2].",
          "citations": [
            "W4291109444",
            "W2758953075",
            "W4225434615",
            "W2757450262",
            "W2204765864",
            "W2257545119",
            "W2588446734",
            "W2500783958",
            "W2036383665",
            "W4224253557",
            "W4280521113"
          ],
          "tables_in_text": [],
          "citations_unmapped": [
            "2"
          ]
        },
        {
          "subsection_id": "s_5_4",
          "subsection_index": 4,
          "subsection_label": "4.4. RQ3: Is Digital Literacy an Essential Construct in Metaverse-Based Blended English Learning?",
          "subsubsections": [],
          "text": "Overall, instructors and students lack digital literacy in using educational metaverse [W1993410685, W3109876850, W4200069166, W4295123432, UNMAPPED:80]. The technical skills of interacting in the metaverse significant predict levels of digital literacy [W3109876850]. Digital literacy is not merely a simple competence to use state-of-the-art technology to improve learning but a process that can continuously change and adapt to improve learning and teaching quality [W2273638022]. Literature has pointed out that high-tech equipment, immersive virtual environments, and a practical text-based course design in an education-based metaverse are essential for teacher digital literacy [W4225434615]. On the other hand, learners may not be familiar with the metaverse and its use for learning, and a purposeful sampling technique should be introduced to learners [W4293168945].\n\nCultivating digital literacy must be improved to support instructors and learners to access metaverse technologies [W4206460460, W4320070415]. The ability to use the digital system does affect the willingness and readiness of English learners to organize language learning activities in the metaverse era. Furthermore, a lack of digital literacy in using the metaverse will cause certain technology anxiety among learners, especially \"technology-na\u00efve\" or underachieved learners [W4293084330]. The metaverse-based technologies require the improvement of instructors' and learners' digital literacy [W2257545119]. There is still a skill gap between using the new platforms and the competence of instructors and the learners' digital literacy [W2036383665]. In addition, the degree of digital literacy is an important factor in sustaining online English education [W4206460460, W4320070415]. For instance, if English instructors can quickly apply different technological means to use digital resources, English learners can be more intuitive to adopting online learning [W3109876850].",
          "citations": [
            "W1993410685",
            "W3109876850",
            "W4200069166",
            "W4295123432",
            "W2273638022",
            "W4225434615",
            "W4293168945",
            "W4206460460",
            "W4320070415",
            "W4293084330",
            "W2257545119",
            "W2036383665"
          ],
          "tables_in_text": [],
          "citations_unmapped": [
            "80"
          ]
        },
        {
          "subsection_id": "s_5_5",
          "subsection_index": 5,
          "subsection_label": "4.5. RQ4: What Are the Challenges on Metaverse-Based Platforms?",
          "subsubsections": [
            {
              "subsubsection_id": "s_5_5_1",
              "subsubsection_index": 1,
              "subsubsection_label": "4.5.1. Gamification",
              "parent_subsection_id": "s_5_5",
              "text": "The metaverse provides game design to extend learner learning experiences, but the game sessions may weaken learner engagement and lead to terrible learning outcomes [W1993410685]. The metaverse is considered the only online game, a significant risk to young learners. The metaverse tools have unique characteristics, such as 3D interactive simulation and real-world physics, so the platform's learning process is similar to gamification [W2114058809]. In addition, a gamified interaction may lack sufficient instructor supervision. It is difficult for instructors to effectively supervise learners' immersive learning activities with a virtual presence [W4206538191]. Fear of high self-regulation and self-control, learners tend to obtain poor learning outcomes.",
              "citations": [
                "W1993410685",
                "W2114058809",
                "W4206538191"
              ],
              "tables_in_text": []
            },
            {
              "subsubsection_id": "s_5_5_2",
              "subsubsection_index": 2,
              "subsubsection_label": "4.5.2. Social Distancing",
              "parent_subsection_id": "s_5_5",
              "text": "The metaverse, which provides high immersion through visualization, may cause users to feel socially distant as learners, as it attracts users with the same hobbies and interests to interact and communicate in virtual environments [W2982503889]. The metaverse may cause a risk of learner isolation, although it creates learner autonomy [W4291466020]. It supports virtual social connection even in the real world, which may lead to social distancing or social alienation [W2982503889]. Therefore, the metaverse may weaken social interactions [W4295873136]. In the field of English education, users may transmit the wrong information, \"me I want to show\" instead of \"me as I am,\" so that the instructor and administrators cannot predict the actual intercultural communication competencies and language skills in the virtual environment. worlds [UNMAPPED:13]. This case is more dangerous than learners of existing online games [W4200069166]. Furthermore, underachieved learners with low engagement or weak self-control may feel hard to adapt to the metaverse technologies. Thus, they tend to feel social alienation [W4200069166].",
              "citations": [
                "W2982503889",
                "W4291466020",
                "W4295873136",
                "W4200069166"
              ],
              "tables_in_text": [],
              "citations_unmapped": [
                "13"
              ]
            },
            {
              "subsubsection_id": "s_5_5_3",
              "subsubsection_index": 3,
              "subsubsection_label": "4.5.3. Deficient Support",
              "parent_subsection_id": "s_5_5",
              "text": "The metaverse technologies have foregrounded deficient education support [UNMAPPED:13]. The metaverse-based education heavily depends on the economic status of universities [W4295873136]. Policymakers and administrators may estimate the improvement of the education reform and learner educational benefits on all files [UNMAPPED:85]. Technical input is another challenge facing metaverse-based education. The internet is the main factor for online learning effectiveness [W4226350846]. Due to the inconvenient Internet connection, the metaverse platforms are still totally or partially out of service [UNMAPPED:80]. Consequently, instructors and learners may feel hesitant to access or interact in the metaverse-based learning process, much less within the specified time of the course [W1939647417].",
              "citations": [
                "W4295873136",
                "W4226350846",
                "W1939647417"
              ],
              "tables_in_text": [],
              "citations_unmapped": [
                "13",
                "85",
                "80"
              ]
            }
          ],
          "text": "The high degree of freedom of the metaverse has appeared to be some challenges in applying language education [W1939647417, W2273638022, W2759268923, W4226350846, W4295873136]. Challenges may include gamification, social distancing, and internet availability.",
          "citations": [
            "W1939647417",
            "W2273638022",
            "W2759268923",
            "W4226350846",
            "W4295873136"
          ],
          "tables_in_text": []
        }
      ],
      "subsubsections": [],
      "text": "",
      "citations": [],
      "tables_in_text": []
    },
    {
      "section_id": "s_6",
      "section_index": 6,
      "section_label": "5. Discussion",
      "subsections": [
        {
          "subsection_id": "s_6_1",
          "subsection_index": 1,
          "subsection_label": "5.1. A New Direction of the Blended Learning",
          "subsubsections": [],
          "text": "The metaverse-based blended learning plays an important role in linking the virtual worlds and the context of real face-to-face classroom learning [W3109876850]. It can effectively improve learners' academic performance by providing the immersion principle in 360-degree panoramic images [W4225434615]. The metaverse technologies enable an individualized and encompassing English learning experience that ranges from a real classroom English education context to a virtual environment [W4226350846]. The unique two-way interaction supported by the metaverse technologies lays the foundation for sustainable English learning [W2982503889]. The metaverse-based blended learning can significantly improve learners' engagement and their learning outcomes.\n\nDue to the rapid development of metaverse technologies, the value of integrating immersive virtual environments into blended English learning has brought awareness to educators and researchers [W2982503889]. Undoubtedly, it is still in its infancy using metaverse-based blended learning [W4244811727]. Concerns with the economy, culture, politics and even personal information security caused by the metaverse technology can be solved properly [W4295873136]. Furthermore, developers and designers of the metaverse platforms could design easier and more convenient tools which can directly or indirectly stimulate language instructors' and learners' readiness in the teaching-learning process [UNMAPPED:13].",
          "citations": [
            "W3109876850",
            "W4225434615",
            "W4226350846",
            "W2982503889",
            "W4244811727",
            "W4295873136"
          ],
          "tables_in_text": [],
          "citations_unmapped": [
            "13"
          ]
        },
        {
          "subsection_id": "s_6_2",
          "subsection_index": 2,
          "subsection_label": "5.2. Perceived Learner Engagement",
          "subsubsections": [],
          "text": "The observed degree of learner engagement based on the education-based metaverse can be comprehensively improved [W2759268923]. The education-based metaverse can improve English learner engagement by providing 3D recreation and language learning opportunities [W2758953075]. However, some learners may hesitate to the metaverse technologies and not be ready to engage at the onset of learning [W2759268923]. Sustainable engagement calls for more interaction with the instructors and peers. Especially for mature students in English learning, instructor support is primary for them to fulfill English learning activities in the metaverse environment [W2759268923]. Familiarity with the platform and accomplishment of the learning tasks with instructor assistance are indispensable parts of learner engagement.\n\nMoreover, it is meritorious to facilitate the lower degree of English learners' engagement in online virtual learning ease [W2758126666]. A blended learning environment utilizing the metaverse may concern English learners' ability to engage, or English learning in a virtual world causes frustration and annoyance, which trigger learner distraction and a lower degree of engagement [W2759268923]. It is beneficial to build up work teams or collaborative learning to passionate them to engage in learning in a wider community of virtual space [W4226474524]. The instructors can also provide one-to-one guidance to help them ease learning anxiety in a virtual world [W4296112744]. However, low-level resistance to engaging with the metaverse may still exist, as revealed in learners' English pedagogy questions or the metaverse platforms.",
          "citations": [
            "W2759268923",
            "W2758953075",
            "W2758126666",
            "W4226474524",
            "W4296112744"
          ],
          "tables_in_text": []
        },
        {
          "subsection_id": "s_6_3",
          "subsection_index": 3,
          "subsection_label": "5.3. Learning Outcomes Improvement",
          "subsubsections": [],
          "text": "The immersive learning experience positively affects learners' emotions and learning effectiveness which influence the engagement of English learning, activate learners' autonomy, and determine learning outcomes [W4224253557]. Metaverse technology generates immersion that differs from psychological immersion [W4224253557]. Technology-based immersion relates to the depth of users' involvement with academic activities in a gameplay model [W4293168945]. Well-designed games with a given task can foster learners' learning performance with immersive virtual environments [W3041286989]. However, it is impossible to provide relative complicate games to support language learners' multi-dimensional learning activities in the real world [W2273638022]. Gameful experiences can promote users' intrinsic and extrinsic motivations to achieve academic success in the virtual world [W2273638022]. Appropriate gamification design in the metaverse technology can stimulate users' willingness to get higher grades in blended English learning [W4293168945].\n\nFurthermore, metaverse-based immersive language learning can cultivate learners' intercultural awareness and critical thinking in authentic virtual worlds. Consciousness and thinking can help language learners become more likely to be closer to the target language community [W2757450262]. The metaverse's main feature is that it solves the language learning scenario's main constraints through authentic virtual environments [W4225434615]. The virtual environments, as the mediation of tacit knowledge, provoke deeper-level thinking processes, which is crucial to the effectiveness of English language learners. Some successful language learners are adept at innovative learning resources of virtual worlds to achieve better learning outcomes.",
          "citations": [
            "W4224253557",
            "W4293168945",
            "W3041286989",
            "W2273638022",
            "W2757450262",
            "W4225434615"
          ],
          "tables_in_text": []
        },
        {
          "subsection_id": "s_6_4",
          "subsection_index": 4,
          "subsection_label": "5.4. Digital Literacy Enhancement",
          "subsubsections": [],
          "text": "Digital literacy is important for accomplishing learning tasks in the metaverse platforms. Learners and instructors are not viewers in the virtual world of the metaverse [UNMAPPED:13]. It would be beneficial to elevate their degree of digital competitiveness in the metaverse [W4295123432]. For instance, learners may accomplish the primary training tasks: basic knowledge of the metaverse technology, major features of the metaverse devices, and the use of the metaverse applications [UNMAPPED:85]. Instructors' digital literacy ability requires fundamental knowledge of metaverse technologies [UNMAPPED:85]. Thus, it is necessary to establish a motivation system for mastering the knowledge and skills of the metaverse because it has been noted that the technology and resources to improve the digital literacy of English learners and instructors are insufficient, especially in teacher education schools [W4224216565].\n\nMoreover, some aspects of digital literacy need to be polished based on digital pedagogical discipline models [W4294865070]. For instance, the technology training of English instructors needs follows the type of metaverse tools which can consolidate English teaching and learning. In addition, instructors can be familiar with instructional and technological interactions (e.g., exchanges between students, managing the software, handling computer-based prompts, etc.) [W4206460460, W4320070415]. Instructors also need to make sense of the entire system of metaverse-based applications [W4280521113]. Furthermore, a high degree of digital literacy can significantly promote the development of the compulsive competence use of communication and information technologies in higher English education [W1999256366]. Therefore, digital literacy on metaverse-based applications requires expanding English instructors' knowledge of specific digital tools and management, and instructors' interaction with learners can be quick in metaverse-based platforms [W2036383665]. Therefore, the enhancement of digital literacy should adapt English study plans; training activities might be dynamic to follow related curricular criteria [W3109876850]. It is necessary to improve instructors' and learners' digital literacy according to context-appropriated frameworks for language learning [UNMAPPED:80]. The perceptive satisfaction degree of digital literacy can be gauged, ranging from instructor to learner based on their attitude toward English courses [W4291109444].",
          "citations": [
            "W4295123432",
            "W4224216565",
            "W4294865070",
            "W4206460460",
            "W4320070415",
            "W4280521113",
            "W1999256366",
            "W2036383665",
            "W3109876850",
            "W4291109444"
          ],
          "tables_in_text": [],
          "citations_unmapped": [
            "13",
            "85",
            "80"
          ]
        },
        {
          "subsection_id": "s_6_5",
          "subsection_index": 5,
          "subsection_label": "5.5. Embracing Challenges",
          "subsubsections": [],
          "text": "The metaverse-based smart education provides us with more opportunities as well as challenges. Based on the high degree of freedom, instructors should be cautious that learners misuse educational metaverse platforms [W4295873136]. Gamification in enhancing academic achievement has two faces: it provides shared 3D entertainment and learning opportunities [W2273638022, W4295873136]. It is necessary for instructors to carefully evaluate learners' learning activity patterns, level of immersion in the metaverse, and their behavioral intentions to use the metaverse [W4224253557]. An innovative education strategy should cover each teaching link to help learners achieve learning goals [W4225434615]. To optimize the usefulness of metaverse-based language education, instructors should manage various resources to fulfill specific language learning tasks under the learning model by doing in the metaverse applications [W3109876850]. In addition, instructors and managers can act as facilitators and guides to assist learners in their training [W2273638022].\n\nThe metaverse-enhanced learning can be monitored to avoid learners feeling socially distant [W1583636700]. Educators and administrators can use more effective English learning materials and more exact virtual environments that can fully foster learning activities [W2139782915]. They can gradually improve the function to increase learners' perceptions of being in the \"real world\" and belonging to a learning community. The metaverse platform developers may pay more attention to designing 3D virtual learning worlds that emphasize emotional achievements, learning support, and the desired learning outcomes [W2114058809, W2588446734]. They can design online applications to enhance supervision over learning behaviors and provide reminders when learners behave improperly [W4291466020].\n\nPossible solutions can be taken into account to financially and technologically support metaverse-based education [W1939647417, W4295873136]. Policymakers and administrators could conform to the educational trend. Otherwise, traditional education models will be hard to support remote education, especially during the emergent period [W4280521113]. We have amazed to see that leading universities in China and worldwide have developed and implemented their own 3D virtual campus environments in instructional processes [W2588446734]. The metaverse developers should improve the compatibility of different hardware and software to reduce instructors' and learners' stress and anxiety [W4285242702]. The developers can design offline sections to enlarge opportunities to access the metaverse platforms. Digital infrastructures could solve technical issues and establish a specialized department to manage and supervise the metaverse platforms [W4291466020, W4224234154].",
          "citations": [
            "W4295873136",
            "W2273638022",
            "W4224253557",
            "W4225434615",
            "W3109876850",
            "W1583636700",
            "W2139782915",
            "W2114058809",
            "W2588446734",
            "W4291466020",
            "W1939647417",
            "W4280521113",
            "W4285242702",
            "W4224234154"
          ],
          "tables_in_text": []
        }
      ],
      "subsubsections": [],
      "text": "The study attempts to integrate the evidence to generate a model that links the education-based metaverse. The metaverse platforms in which learners' academic success can be significantly enhanced due to a high degree of learner engagement in immersive virtual environments. In addition, the virtual learning experience is restricted by the degree of digital literacy at the same time. To improve instructors' and learners' digital literacy levels, necessary support is indispensable by educational institutions and developers and designers of the metaverse platforms.",
      "citations": [],
      "tables_in_text": []
    },
    {
      "section_id": "s_7",
      "section_index": 7,
      "section_label": "6. Conclusions",
      "subsections": [
        {
          "subsection_id": "s_7_1",
          "subsection_index": 1,
          "subsection_label": "6.1. Major Findings",
          "subsubsections": [],
          "text": "This study aims to investigate the education-based metaverse to sustain the current blended English learning during the post-pandemic era by examining some significant factors. The main factors are learner engagement, learning outcomes, and digital literacy. Meanwhile, this study addresses potential challenges that may hinder sustaining metaverse-based blended English learning.\n\nOnce the metaverse mixes English education, it can reshape the prior blended English learning. The metaverse can provide affluent, direct, and indirect learning opportunities, greatly enhancing English learners' learning readiness and intuition. The education-based metaverse can positively promote English user engagement. The immersive learning experience in the education-based metaverse can positively promote English learning outcomes. Digital literacy on metaverse-based technologies is an essential construct in metaverse-based blended English learning. The features of high freedom of the metaverse have appeared as challenges in the application of language education. Challenges may include gamification, social distancing, and internet availability. This study has provided some suggestions according to the previous literature.\n\nA quality learning environment is meaningful learners do better at creative and critical thinking skills [W2114003275]. The most significant aspect of this study has been the need to explore the opportunity to enhance the effectiveness and efficiency of teaching and learning, which may bring successful responses to learners' needs, such as wellbeing and positive emotion. The core values of learner positive emotion can produce a psychological state favorable to learning [W4200302524]. Furthermore, with advances in information and communication technologies, blended learning can be well-updated through technology-mediated education, such as the metaverse and other online learning tools. This study aims to reveal that the metaverse-based technology implements and sustains effective blended learning environments, which may enhance learner spirits and create positive momentum for language learning.\n\nThere are four types of the metaverse which have developed independently: (1) Augmented reality: a smart environment can be built to augment the real physical world based on location-based technology [W2229756981]. A representative educational case is that language learners can effectively obtain learning materials that cannot be presented in texts via smartphones or vehicle HUDs (head-up display) [W4200069166]. When language learners require continuous experience or practice, augmented reality technology allows learners to link abstract visuals to concrete objects and solve English reading, writing, or speaking problems [W3098871788]. (2) Lifelogging: a world of lifelogging is an augmentation of the inner world that can be recorded and analyzed through augmented technology [W4200069166]. For example, learners' daily learning activities and thoughts can be shared through social media, such as Facebook and Apple Watch [W4200069166]. A typical example of education is that learners' learning achievements can be analyzed. For instructors, it provides them valuable feedback, which leads to reinforcement and an appropriate teaching direction [W4285585446]. (3) Mirror world: a simulation or reflection of the real world [W2229756981]. All activities in the mirror world can be done based on mobile applications [W4285585446]. A representative of a mirror world metaverse used in education is digital laboratories or real-time online classes via online video conferencing tools (such as Zoom and Tencent Conference) [W4200069166]. Learners can overcome the physical or special limitations of learning in the mirror world metaverse [W4200069166]. English learners can realize non-face-to-face remote learning, which presents great educational potential [W4285585446]. (4) Virtual reality: a combination of a virtual world and real-world built with digital data is, to some degree, the most complete of virtual reality [W4220819629]. This virtual reality metaverse dramatically enlarged the scope of educational spaces based on a complex of virtual reality technologies (such as avatars, 3D graphics, and instant communication tools) [W4200069166]. A representative example of metaverse-based education is that learning can be performed via instant communication tools (such as Second Life, Minecraft, Roblox, and Zepeto) [W4220819629]. English learners can simultaneously access and perform meaningful tasks in immersive virtual environments [W4200069166]. The metaverse provides customized learning levels [W4220819629]. Furthermore, it breaks the boundaries between the abovementioned types of metaverse [W4200069166].\n\nThis study provides theoretical implications and practical guidelines for educators and researchers to enhance the metaverse-based blended English learning construction. This study shows that higher-immersion environments create higher levels of presence and better learning outcomes. Based on the characteristics of the metaverse, the researchers support that the metaverse is an evolved concept. More importantly, metaverse-based education performs important missions in blended education contexts. The metaverse platforms provide not merely online games but self-directed learning experiences. On the other hand, the metaverse makes it possible to expand the scope of English education. It is predicted to improve learners' academic performance and significantly expand their freedom to explore questions. However, appropriate regulations and measures are necessary for both instructors and learners to adopt metaverse-assisted methods for educational purposes.",
          "citations": [
            "W2114003275",
            "W4200302524",
            "W2229756981",
            "W4200069166",
            "W3098871788",
            "W4285585446",
            "W4220819629",
            "W4206538191",
            "W4226350846"
          ],
          "tables_in_text": [],
          "citations_unmapped": [
            "2"
          ]
        },
        {
          "subsection_id": "s_7_2",
          "subsection_index": 2,
          "subsection_label": "6.2. Limitations",
          "subsubsections": [],
          "text": "There are several limitations to this study. First, it should be acknowledged that studies cited in this review may be insufficient, owing to the databases and keywords used in this systematic review. Second, the findings of this study are limited by the author's resource availability. Third, this study only reviews English academic articles about the metaverse in education. Some interesting and meaningful findings might be neglected, which might lead to the deviation of the research findings in this study. Fourth, due to the immaturity of the metaverse and lack of sufficient published studies identified from the Web of Science and Scopus databases, this study cannot capture the whole picture of the research.",
          "citations": [],
          "tables_in_text": []
        },
        {
          "subsection_id": "s_7_3",
          "subsection_index": 3,
          "subsection_label": "6.3. Future Research Directions",
          "subsubsections": [],
          "text": "In future research, we will keep updating and polishing the metaverse-based blended English learning research. Due to the immaturity of metaverse-based blended English learning, this study cannot provide the overall research findings. In addition, we may add more practical features, such as self-efficacy, the degree of satisfaction, technology anxiety, etc. With advances in metaverse technology, we may enrich the systematic review by building a theoretical model on metaverse-based blended English learning. Meanwhile, instructional tools and advanced evaluative measures will be used.\n\nAnother direction of future research on metaverse-based blended English learning may be to reveal the metaverse-based applications and their effects on learners' motivation through an empirical study. The findings of this study show that metaverse technologies can enhance the efficiency of language learning and improve learners' learning outcomes; at the same time, the mixture of the metaverse has brought some challenges, such as a lower level of instructor and learner digital literacy. In the future, it is necessary to empirically investigate the advantages and disadvantages of the metaverse to sustain blended English learning. We may empirical studies to analyze and calculate the effect of the metaverse on blended English learning in higher education.",
          "citations": [],
          "tables_in_text": []
        }
      ],
      "subsubsections": [],
      "text": "",
      "citations": [],
      "tables_in_text": []
    },
    {
      "section_id": "s_8",
      "section_index": 8,
      "section_label": "Author Contributions",
      "subsections": [],
      "subsubsections": [],
      "text": "Both authors listed have made a substantial, direct, and intellectual contribution to the work and approved it for publication.",
      "citations": [],
      "tables_in_text": []
    },
    {
      "section_id": "s_9",
      "section_index": 9,
      "section_label": "Funding",
      "subsections": [],
      "subsubsections": [],
      "text": "The project is supported by the Fundamental Research Funds for the Central Universities, and the Research Funds of Beijing Language and Culture University (Blended English Learning During the Post-Epidemic Era, 22YCX102). This work is supported by 2019 MOOC of Beijing Language and Culture University (MOOC201902) (Important), Introduction to Linguistics. Introduction to Linguistics of online and offline mixed courses in Beijing Language and Culture University in 2020. Special fund of Beijing Co-construction Project-Research and reform of the Undergraduate Teaching Reform and Innovation Project of Beijing Higher Education in 2020-innovative multilingual+ excellent talent training system (202010032003). The research project of Graduate Students of Beijing Language and Culture University, Xi Jinping: The Governance of China (SJTS202108).",
      "citations": [],
      "tables_in_text": [],
      "citations_unmapped": [
        "202010032003"
      ]
    },
    {
      "section_id": "s_10",
      "section_index": 10,
      "section_label": "Conflict of Interest",
      "subsections": [],
      "subsubsections": [],
      "text": "The authors declare that the research was conducted in the absence of any commercial or financial relationships that could be construed as a potential conflict of interest.",
      "citations": [],
      "tables_in_text": []
    },
    {
      "section_id": "s_11",
      "section_index": 11,
      "section_label": "Publisher's Note",
      "subsections": [],
      "subsubsections": [],
      "text": "All claims expressed in this article are solely those of the authors and do not necessarily represent those of their affiliated organizations, or those of the publisher, the editors and the reviewers. Any product that may be evaluated in this article, or claim that may be made by its manufacturer, is not guaranteed or endorsed by the publisher.",
      "citations": [],
      "tables_in_text": []
    }
  ],
  "tables": [],
  "tables_file": "W4313595551_tables.md"
}
